{
  "category_id": "584240da54be81056cecac48",
  "category_name": "Social and Behavioral Sciences",
  "groups": [
    {
      "id": "584240da54be81056cecac1a",
      "name": "Political Science",
      "osf_subjects": [
        {
          "id": "584240da54be81056cecac1a",
          "name": "Political Science"
        }
      ]
    },
    {
      "id": "584240da54be81056cecab8f",
      "name": "Economics",
      "osf_subjects": [
        {
          "id": "584240da54be81056cecab8f",
          "name": "Economics"
        }
      ]
    },
    {
      "id": "584240da54be81056cecac6a",
      "name": "Sociology",
      "osf_subjects": [
        {
          "id": "584240da54be81056cecac6a",
          "name": "Sociology"
        }
      ]
    }, 
    {
      "id": "584240d954be81056ceca8be",
      "name": "Communication",
      "osf_subjects": [
        {
          "id": "584240d954be81056ceca8be",
          "name": "Communication"
        }
      ]
    },
    {
      "id": "584240da54be81056cecaab8",
      "name": "Public Affairs, Public Policy and Public Administration",
      "osf_subjects": [
        {
          "id": "584240da54be81056cecaab8",
          "name": "Public Affairs, Public Policy and Public Administration"
        }
      ]
    },
    {
      "id": "584240da54be81056cecabae",
      "name": "Environmental Studies",
      "osf_subjects": [
        {
          "id": "584240da54be81056cecabae",
          "name": "Environmental Studies"
        }
      ]
    },
   {
      "id": "584240da54be81056c000000",
      "name": "(Other)",
      "osf_subjects": [
        {
          "id": "59baec7354be810242f55303",
          "name": "Food Studies"
        },
        {
          "id": "584240db54be81056cecacf6",
          "name": "Geography"
        },
        {
          "id": "584240db54be81056cecacbc",
          "name": "International and Area Studies"
        },
        {
          "id": "584240da54be81056cecac69",
          "name": "Urban Studies and Planning"
        },
        {
          "id": "584240da54be81056cecac68",
          "name": "Psychology"
        },
        {
          "id": "584240da54be81056cecabde",
          "name": "Agricultural and Resource Economics"
        },
        {
          "id": "584240da54be81056cecabcd",
          "name": "Legal Studies"
        },
        {
          "id": "584240da54be81056cecab71",
          "name": "Social Work"
        },
        {
          "id": "584240da54be81056cecab6c",
          "name": "Leisure Studies"
        },
        {
          "id": "584240da54be81056cecab37",
          "name": "Leadership Studies"
        },
        {
          "id": "584240da54be81056cecab36",
          "name": "Counseling"
        },
        {
          "id": "584240da54be81056cecab33",
          "name": "Library and Information Science"
        },
        {
          "id": "584240d954be81056ceca9ae",
          "name": "Animal Studies"
        },
        {
          "id": "584240d954be81056ceca9ad",
          "name": "Science and Technology Studies"
        },
        {
          "id": "584240d954be81056ceca99c",
          "name": "Sports Studies"
        },
        {
          "id": "584240d954be81056ceca97d",
          "name": "Anthropology"
        },
        {
          "id": "584240d954be81056ceca960",
          "name": "Linguistics"
        },
        {
          "id": "584240d954be81056ceca919",
          "name": "Social Statistics"
        },
        {
          "id": "584240d954be81056ceca895",
          "name": "Organization Development"
        },
        {
          "id": "584240da54be81056cecac85",
          "name": "Other Social and Behavioral Sciences"
        }
      ]
    },  
    {
      "id": "584240da54be81056cXXXXXX",
      "name": "(Not classified)"
    }
  ]
}